dahuffman/__init__.py
dahuffman/huffmancodec.py
dahuffman/codecs/__init__.py
dahuffman/codecs/json-compact.pickle
dahuffman/codecs/json.pickle
dahuffman/codecs/shakespeare-lower.pickle
dahuffman/codecs/shakespeare-raw.pickle
dahuffman/codecs/shakespeare.pickle
dahuffman/codecs/xml.pickle
dahuffman-0.4.1.dist-info/LICENSE.txt
dahuffman-0.4.1.dist-info/METADATA
dahuffman-0.4.1.dist-info/WHEEL
dahuffman-0.4.1.dist-info/top_level.txt
dahuffman-0.4.1.dist-info/RECORD
