Metadata-Version: 1.1
Name: dahuffman
Version: 0.4.1
Summary: Pure Python Huffman encoder and decoder module
Home-page: https://github.com/soxofaan/dahuffman
Author: Stefaan Lippens
Author-email: soxofaan@gmail.com
License: MIT
Keywords: huffman compression encoding decoding
Platform: UNKNOWN
Classifier: Intended Audience :: Developers
Classifier: Topic :: System :: Archiving :: Compression
Classifier: License :: OSI Approved :: MIT License
Classifier: Programming Language :: Python :: 3
